{
    "asset": {
        "format": "jpg",
        "id": "3d7b7f3963a11560f0d24024bfbcc921",
        "name": "1_31.jpg",
        "path": "file:C:/Users/MadhuVasanth1606/Desktop/yolo_structure/Data/Source_Images/Training_Images/1_31.jpg",
        "size": {
            "width": 294,
            "height": 222
        },
        "state": 2,
        "type": 1
    },
    "regions": [
        {
            "id": "BCbsmzrdi",
            "type": "RECTANGLE",
            "tags": [
                "Atopic Dermatitis"
            ],
            "boundingBox": {
                "height": 53.950716666987375,
                "width": 55.375453566086776,
                "left": 199.6431449124361,
                "top": 75.70876609163331
            },
            "points": [
                {
                    "x": 199.6431449124361,
                    "y": 75.70876609163331
                },
                {
                    "x": 255.01859847852288,
                    "y": 75.70876609163331
                },
                {
                    "x": 255.01859847852288,
                    "y": 129.6594827586207
                },
                {
                    "x": 199.6431449124361,
                    "y": 129.6594827586207
                }
            ]
        },
        {
            "id": "8CY0VJITA",
            "type": "RECTANGLE",
            "tags": [
                "Atopic Dermatitis"
            ],
            "boundingBox": {
                "height": 42.285703161079894,
                "width": 75.04831601961837,
                "left": 110.02232706856994,
                "top": 97.58068727389933
            },
            "points": [
                {
                    "x": 110.02232706856994,
                    "y": 97.58068727389933
                },
                {
                    "x": 185.07064308818832,
                    "y": 97.58068727389933
                },
                {
                    "x": 185.07064308818832,
                    "y": 139.86639043497922
                },
                {
                    "x": 110.02232706856994,
                    "y": 139.86639043497922
                }
            ]
        }
    ],
    "version": "2.2.0"
}